langchain_guidelines/__init__.py
langchain_guidelines/_modidx.py
langchain_guidelines/core.py
langchain_guidelines-0.0.1.dist-info/LICENSE
langchain_guidelines-0.0.1.dist-info/METADATA
langchain_guidelines-0.0.1.dist-info/WHEEL
langchain_guidelines-0.0.1.dist-info/entry_points.txt
langchain_guidelines-0.0.1.dist-info/top_level.txt
langchain_guidelines-0.0.1.dist-info/RECORD
